{
  "schema": "autoskill.document.parent_children_manifest.v1",
  "generated_at": "2026-03-22T13:19:09+00:00",
  "domain_root_name": "心理咨询",
  "family_name": "后现代主义",
  "profile_id": "psychology::后现代主义",
  "taxonomy_axis": "疗法",
  "parent_skill_id": "670baf21-ee62-5f3d-8884-87dd60f67944",
  "parent_name": "家族图品质标注与脉络觉察",
  "children": [
    {
      "skill_id": "c5dc92ca-dac4-5668-9e82-4ebeb7eb1d97",
      "name": "家族图叙说与品质标注",
      "description": "引导来访者绘制并叙说家族图，为每位家庭成员标注三个正向品质、三个负向品质及重大家族事件，以支持家庭系统影响的外化、资源识别与关系脉络觉察。",
      "child_type": "叙事重构",
      "asset_node_id": "micro_intervention",
      "asset_path": "family_root/treatment_framework/session_framework/micro_intervention",
      "asset_level": 3,
      "parent_skill_id": "670baf21-ee62-5f3d-8884-87dd60f67944",
      "level_label": "微技能",
      "taxonomy_class": "后现代主义",
      "applicable_when": "引导来访者绘制并叙说家族图，为每位家庭成员标注三个正向品质、三个负向品质及重大家族事件，以支持家庭系统影响的外化、资源识别与关系脉络觉察。",
      "selector_terms": [
        "来访者关系困扰与家庭背景相关",
        "需启动资源取向探索",
        "咨询初期建立合作性对话",
        "叙事疗法",
        "家族图",
        "资源取向",
        "外化技术",
        "家族图叙说与品质标注"
      ],
      "relative_path": "心理咨询/Family技能/后现代主义/微技能/家族图叙说与品质标注/SKILL.md"
    },
    {
      "skill_id": "20275759-06e2-527a-be43-aaf5bf4c6ab6",
      "name": "萨提亚式'我是谁'结构化探索",
      "description": "按名、性格、角色三维度结构化引导来访者自我描述，聚焦自我关系体验与自动化思维时段觉察。",
      "child_type": "自我概念探索",
      "asset_node_id": "micro_intervention",
      "asset_path": "family_root/treatment_framework/session_framework/micro_intervention",
      "asset_level": 3,
      "parent_skill_id": "670baf21-ee62-5f3d-8884-87dd60f67944",
      "level_label": "微技能",
      "taxonomy_class": "后现代主义",
      "applicable_when": "按名、性格、角色三维度结构化引导来访者自我描述，聚焦自我关系体验与自动化思维时段觉察。",
      "selector_terms": [
        "来访者自我感模糊或关系中过度适应",
        "需非病理化方式激活主体性",
        "已建立基本咨询联盟",
        "后现代主义",
        "萨提亚",
        "自我关系",
        "自动化思维",
        "萨提亚式'我是谁'结构化探索"
      ],
      "relative_path": "心理咨询/Family技能/后现代主义/微技能/萨提亚式'我是谁'结构化探索/SKILL.md"
    }
  ]
}