{
  "schema": "autoskill.document.parent_children_manifest.v1",
  "generated_at": "2026-03-23T08:16:33+00:00",
  "domain_root_name": "心理咨询",
  "family_name": "认知行为疗法",
  "profile_id": "psychology::认知行为疗法",
  "taxonomy_axis": "疗法",
  "parent_skill_id": "778d965e-3258-53a1-960f-a11ecbe5cd2c",
  "parent_name": "DBT问题行为优先界定",
  "children": [
    {
      "skill_id": "fd689910-e67d-53be-9898-a10bde212be8",
      "name": "DBT问题行为优先级界定",
      "description": "依据DBT临床优先级规则（生命威胁行为 > 治疗干扰行为 > 质量-of-life干扰行为），与来访者协作将当前最紧迫问题行为锚定为自伤行为，并明确其为本次治疗焦点。",
      "child_type": "behavioral assessment",
      "asset_node_id": "micro_intervention",
      "asset_path": "family_root/treatment_framework/session_framework/micro_intervention",
      "asset_level": 3,
      "parent_skill_id": "778d965e-3258-53a1-960f-a11ecbe5cd2c",
      "level_label": "微技能",
      "taxonomy_class": "认知行为疗法",
      "applicable_when": "依据DBT临床优先级规则（生命威胁行为 > 治疗干扰行为 > 质量-of-life干扰行为），与来访者协作将当前最紧迫问题行为锚定为自伤行为，并明确其为本次治疗焦点。",
      "selector_terms": [
        "来访者报告或观察到自伤行为",
        "存在多个待处理问题行为",
        "需启动DBT行为链分析",
        "DBT",
        "行为优先级",
        "自伤干预",
        "协作式评估",
        "来访者近期有非自杀性自伤史",
        "治疗动机波动但尚具合作基础",
        "问题列表中包含≥2项可操作的行为目标",
        "DBT问题行为优先级界定",
        "依据DBT临床优先级规则（生命威胁行为 > 治疗干扰行为 > 质量-of-life干扰行为），与来访者协作将当前最紧迫问题行为锚定为自伤行为，并明确其为本次治疗焦点。"
      ],
      "relative_path": "心理咨询/Family技能/认知行为疗法/微技能/DBT问题行为优先级界定/SKILL.md"
    }
  ]
}