{
  "schema": "autoskill.document.parent_children_manifest.v1",
  "generated_at": "2026-03-23T08:16:33+00:00",
  "domain_root_name": "心理咨询",
  "family_name": "认知行为疗法",
  "profile_id": "psychology::认知行为疗法",
  "taxonomy_axis": "疗法",
  "parent_skill_id": "2edd062b-3b01-5eb5-970c-212e9bd33c78",
  "parent_name": "结构化家庭作业反馈循环",
  "children": [
    {
      "skill_id": "bbbc4da6-21e0-5ccd-9067-aeeb2ab4ddd5",
      "name": "家庭作业反馈-认知更新循环",
      "description": "一种标准化的CBT家庭作业反馈微技能：通过确认完成体验→锚定1–2个高信息量事件→三维对比（情绪/想法/躯体）前后变化→共构策略归因→协商场景迁移，将作业转化为可验证的认知改变实证锚点。",
      "child_type": "CBT作业管理",
      "asset_node_id": "micro_intervention",
      "asset_path": "family_root/treatment_framework/session_framework/micro_intervention",
      "asset_level": 3,
      "parent_skill_id": "2edd062b-3b01-5eb5-970c-212e9bd33c78",
      "level_label": "微技能",
      "taxonomy_class": "认知行为疗法",
      "applicable_when": "一种标准化的CBT家庭作业反馈微技能：通过确认完成体验→锚定1–2个高信息量事件→三维对比（情绪/想法/躯体）前后变化→共构策略归因→协商场景迁移，将作业转化为可验证的认知改变实证锚点。",
      "selector_terms": [
        "来访者完成上一次布置的五栏表或行为实验记录",
        "出现情绪/认知变化数据（如评分下降）",
        "来访者愿意讨论作业细节",
        "CBT",
        "作业反馈",
        "认知更新",
        "五栏表",
        "来访者主动提及作业中某次事件的具体细节",
        "情绪自评分数较前次明显下降（≥2分）",
        "使用'我试了…所以…'句式描述变化",
        "家庭作业反馈-认知更新循环",
        "一种标准化的CBT家庭作业反馈微技能：通过确认完成体验→锚定1–2个高信息量事件→三维对比（情绪/想法/躯体）前后变化→共构策略归因→协商场景迁移，将作业转化为可验证的认知改变实证锚点。"
      ],
      "relative_path": "心理咨询/Family技能/认知行为疗法/微技能/家庭作业反馈-认知更新循环/SKILL.md"
    }
  ]
}